pandasdmx/__init__.py
pandasdmx/api.py
pandasdmx/exceptions.py
pandasdmx/message.py
pandasdmx/model.py
pandasdmx/remote.py
pandasdmx/sources.json
pandasdmx/urn.py
pandasdmx/util.py
pandasdmx/format/__init__.py
pandasdmx/format/json.py
pandasdmx/format/protobuf_pb2.py
pandasdmx/format/xml.py
pandasdmx/reader/__init__.py
pandasdmx/reader/base.py
pandasdmx/reader/sdmxjson.py
pandasdmx/reader/sdmxml.py
pandasdmx/source/__init__.py
pandasdmx/source/abs.py
pandasdmx/source/estat.py
pandasdmx/source/insee.py
pandasdmx/source/istat.py
pandasdmx/source/lsd.py
pandasdmx/source/sgr.py
pandasdmx/source/wb.py
pandasdmx/writer/__init__.py
pandasdmx/writer/base.py
pandasdmx/writer/pandas.py
pandasdmx/writer/protobuf.py
pandasdmx/writer/xml.py
pandaSDMX-1.9.0.dist-info/LICENSE
pandaSDMX-1.9.0.dist-info/WHEEL
pandaSDMX-1.9.0.dist-info/METADATA
pandaSDMX-1.9.0.dist-info/RECORD
