Metadata-Version: 2.1
Name: pandaSDMX
Version: 1.9.0
Summary: Statistical Data and Metadata eXchange (SDMX) for the Python data ecosystem
Home-page: https://github.com/dr-leo/pandasdmx
Keywords: statistics, SDMX, pandas, data, economics, science
Author: dr-leo
Author-email: fhaxbox66@gmail.com
Requires-Python: >=3.7.8,<3.11
Classifier: Intended Audience :: Developers
Classifier: Intended Audience :: Science/Research
Classifier: Intended Audience :: Financial and Insurance Industry
Classifier: Development Status :: 4 - Beta
Classifier: Operating System :: OS Independent
Classifier: Programming Language :: Python :: 3.7
Classifier: Programming Language :: Python :: 3.8
Classifier: Programming Language :: Python :: 3.9
Classifier: Programming Language :: Python :: 3.10
Classifier: Topic :: Scientific/Engineering
Classifier: Topic :: Scientific/Engineering :: Information Analysis
Classifier: License :: OSI Approved :: Apache Software License
Requires-Dist: requests >=2.15
Requires-Dist: lxml >= 4.1
Requires-Dist: pandas >= 1.2
Requires-Dist: pydantic >=1.8.1, < 3.10
Requires-Dist: requests_cache ; extra == "cache"
Requires-Dist: sphinx >= 2.3 ; extra == "doc"
Requires-Dist: IPython ; extra == "doc"
Requires-Dist: appdirs >= 1.4 ; extra == "schema"
Requires-Dist: pytest >= 5 ; extra == "test"
Requires-Dist: requests-mock >= 1.4 ; extra == "test"
Project-URL: Homepage, https://pandasdmx.readthedocs.io/en/latest/
Provides-Extra: cache
Provides-Extra: doc
Provides-Extra: schema
Provides-Extra: test
